<?xml version='1.0' encoding='ISO-8859-1'?>
<!DOCTYPE toc PUBLIC "-//Sun Microsystems Inc.//DTD JavaHelp TOC Version 2.0//EN"
                     "http://java.sun.com/products/javahelp/toc_2_0.dtd">

<toc version="2.0">
	<tocitem text="MSOpentech Tools">
		<tocitem text="About Azure Deployment Project" target="windows_azure_project" />
		<tocitem text="About Azure" target="windows_azure_project_properties" />
		<tocitem text="About Azure Roles" target="windows_azure_project_roles" />
		<tocitem text="About Remote Access" target="windows_azure_project_remote_access_property" />
		<tocitem text="About New Certificate" target="new_certificate_dialog" />
		<tocitem text="About Storage Account" target="storage_account_dialog" />
		<tocitem text="About Debug Configuration" target="windows_azure_debug_config" />
		<tocitem text="About Caching" target="windows_azure_caching_page" />
		<tocitem text="About Certificates" target="windows_azure_certificates_page" />
		<tocitem text="About  Named Cache" target="windows_azure_cache_dialog" />
		<tocitem text="About Endpoints" target="windows_azure_endpoint_page" />
		<tocitem text="About Debugging" target="windows_azure_debug_page" />
		<tocitem text="About Environment Variables" target="windows_azure_envvar_page" />
		<tocitem text="About Local Storage" target="windows_azure_localstorage_page" />
		<tocitem text="About Load Balancing" target="windows_azure_loadbalance_page" />
		<tocitem text="About SSL Offloading" target="windows_azure_ssl_offloading_page" />
		<tocitem text="About Add Component" target="windows_azure_importexport_dialog" />
		<tocitem text="About Server Configuration" target="windows_azure_serverconfiguration_page" />
		<tocitem text="About Components" target="windows_azure_components_page" />
		<tocitem text="About Add Application" target="windows_azure_addapp_dialog" />
		<tocitem text="Publish to Azure from Eclipse" target="publish_project_command" />
		<tocitem text="Create a New Cloud Service" target="new_hosted_service" />
		<tocitem text="Create a New Storage Account" target="new_storage_account" />
		<tocitem text="Unpublish a Deployment from Azure Cloud" target="unpublish_project_command" />
		<tocitem text="About Roles" target="windows_azure_project_roles" />
		<tocitem text="About Azure" target="windows_azure_project_project_property" />
	</tocitem>
</toc>
